cli.py
context_gen-0.1.0.dist-info/licenses/LICENSE
context_gen-0.1.0.dist-info/METADATA
context_gen-0.1.0.dist-info/WHEEL
context_gen-0.1.0.dist-info/entry_points.txt
context_gen-0.1.0.dist-info/top_level.txt
context_gen-0.1.0.dist-info/RECORD
