Metadata-Version: 2.4
Name: context-gen
Version: 0.1.0
Summary: Add your description here
Requires-Python: >=3.11
License-File: LICENSE
Requires-Dist: pathspec>=0.12.1
Dynamic: license-file
